README.txt
setup.py
Products/__init__.py
Products.PFGVerkkomaksut.egg-info/PKG-INFO
Products.PFGVerkkomaksut.egg-info/SOURCES.txt
Products.PFGVerkkomaksut.egg-info/dependency_links.txt
Products.PFGVerkkomaksut.egg-info/entry_points.txt
Products.PFGVerkkomaksut.egg-info/namespace_packages.txt
Products.PFGVerkkomaksut.egg-info/not-zip-safe
Products.PFGVerkkomaksut.egg-info/paster_plugins.txt
Products.PFGVerkkomaksut.egg-info/requires.txt
Products.PFGVerkkomaksut.egg-info/top_level.txt
Products/PFGVerkkomaksut/__init__.py
Products/PFGVerkkomaksut/configure.zcml
Products/PFGVerkkomaksut/setuphandlers.py
Products/PFGVerkkomaksut/skins.zcml
Products/PFGVerkkomaksut/version.txt
Products/PFGVerkkomaksut/browser/__init__.py
Products/PFGVerkkomaksut/browser/configure.zcml
Products/PFGVerkkomaksut/browser/miscellaneous.py
Products/PFGVerkkomaksut/browser/template.py
Products/PFGVerkkomaksut/browser/templates/verkkomaksut.pt
Products/PFGVerkkomaksut/browser/templates/verkkomaksut_success.pt
Products/PFGVerkkomaksut/content/__init__.py
Products/PFGVerkkomaksut/content/configure.zcml
Products/PFGVerkkomaksut/content/formVerkkomaksutAdapter.py
Products/PFGVerkkomaksut/interfaces/__init__.py
Products/PFGVerkkomaksut/interfaces/content_types.py
Products/PFGVerkkomaksut/interfaces/viewlet_manager.py
Products/PFGVerkkomaksut/profiles/default/Products.PFGVerkkomaksut_various.txt
Products/PFGVerkkomaksut/profiles/default/factorytool.xml
Products/PFGVerkkomaksut/profiles/default/import_steps.xml
Products/PFGVerkkomaksut/profiles/default/metadata.xml
Products/PFGVerkkomaksut/profiles/default/rolemap.xml
Products/PFGVerkkomaksut/profiles/default/types.xml
Products/PFGVerkkomaksut/profiles/default/workflows.xml
Products/PFGVerkkomaksut/profiles/default/types/PFGVerkkomaksut.xml
Products/PFGVerkkomaksut/skins/PFGVerkkomaksut/verkkomaksut.pt
Products/PFGVerkkomaksut/tests/__init__.py
Products/PFGVerkkomaksut/tests/base.py
Products/PFGVerkkomaksut/tests/test_content_type_functional.py
Products/PFGVerkkomaksut/tests/test_functional.py
Products/PFGVerkkomaksut/tests/test_setup.py
Products/PFGVerkkomaksut/tests/test_unittest.py
Products/PFGVerkkomaksut/tests/functional/content_types_functional.txt
Products/PFGVerkkomaksut/tests/functional/order_functional.txt
Products/PFGVerkkomaksut/tests/unittest/content_type.txt
docs/CREDITS.txt
docs/HISTORY.txt
docs/INSTALL.txt
docs/LICENSE.GPL
docs/LICENSE.txt