Metadata-Version: 1.0
Name: Products.PFGVerkkomaksut
Version: 0.11.0
Summary: Products.PFGVerkkomaksut provides verkkomaksut payment adapter to Products.PloneFormGen package.
Home-page: http://svn.plone.org/svn/collective/
Author: Taito Horiuchi
Author-email: taito.horiuchi@gmail.com
License: GPL
Platform: UNKNOWN
Classifier: Framework :: Plone
Classifier: Programming Language :: Python
